[{"title":"Priekšvārds","slug":"/prieksvards","url":"/prieksvards/"},{"title":"Autiņā iesēžas sieva un vīrs","slug":"/autina-iesezas-sieva-un-virs","url":"/autina-iesezas-sieva-un-virs/"},{"title":"Bite durvīs uz lodžiju","slug":"/bite-durvis-uz-lodziju","url":"/bite-durvis-uz-lodziju/"},{"title":"Ceļas migla","slug":"/celas-migla","url":"/celas-migla/"},{"title":"Ceļā sirds draudzējas","slug":"/cela-sirds-draudzejas","url":"/cela-sirds-draudzejas/"},{"title":"Epizode 103. sērijas ēkā","slug":"/epizode-103-serijas-eka","url":"/epizode-103-serijas-eka/"},{"title":"Griezts metāls šķind","slug":"/griezts-metals-skind","url":"/griezts-metals-skind/"},{"title":"Iepirkšanās centrs","slug":"/iepirksanas-centrs","url":"/iepirksanas-centrs/"},{"title":"Izvēlēties","slug":"/izveleties","url":"/izveleties/"},{"title":"Kāpnes pieder jaunībai","slug":"/kapnes-pieder-jaunibai","url":"/kapnes-pieder-jaunibai/"},{"title":"Klab zobu rindas","slug":"/klab-zobu-rindas","url":"/klab-zobu-rindas/"},{"title":"Līdzpaņemts alkst veldzēt","slug":"/lidzpanemts-alkst-veldzet","url":"/lidzpanemts-alkst-veldzet/"},{"title":"Māceklis ēnas pusē","slug":"/maceklis-enas-puse","url":"/maceklis-enas-puse/"},{"title":"Mirdz migla","slug":"/mirdz-migla","url":"/mirdz-migla/"},{"title":"Mušu spēja lidināties","slug":"/musu-speja-lidinaties","url":"/musu-speja-lidinaties/"},{"title":"Nakts. Dziļumā koku vainagi","slug":"/nakts-dziluma-koku-vainagi","url":"/nakts-dziluma-koku-vainagi/"},{"title":"nauda, nauda","slug":"/nauda-nauda","url":"/nauda-nauda/"},{"title":"Pavasar","slug":"/pavasar","url":"/pavasar/"},{"title":"Pavēris logu aizkarus, redzu","slug":"/paveris-logu-aizkarus-redzu","url":"/paveris-logu-aizkarus-redzu/"},{"title":"Pīti, akcentam vietām sarkani","slug":"/piti-akcentam-vietam-sarkani","url":"/piti-akcentam-vietam-sarkani/"},{"title":"Puteklīt, tevi aizslaucīs","slug":"/puteklit-tevi-aizslaucis","url":"/puteklit-tevi-aizslaucis/"},{"title":"Rudens toņi gan kokos, gan","slug":"/rudens-toni-gan-kokos-gan","url":"/rudens-toni-gan-kokos-gan/"},{"title":"saknēs iestigušas kājas","slug":"/saknes-iestigusas-kajas","url":"/saknes-iestigusas-kajas/"},{"title":"Skatos, pasaule","slug":"/skatos-pasaule","url":"/skatos-pasaule/"},{"title":"Šalkas","slug":"/salkas","url":"/salkas/"},{"title":"Tikai nešķaudi","slug":"/tikai-neskaudi","url":"/tikai-neskaudi/"},{"title":"Tūdaļ, biezoknī patvērušās","slug":"/tudal-biezokni-patverusas","url":"/tudal-biezokni-patverusas/"},{"title":"Uzmetu kūleni vecmammas","slug":"/uzmetu-kuleni-vecmammas","url":"/uzmetu-kuleni-vecmammas/"}]